codelldb/__init__.py
codelldb/py.typed
codelldb-0.1.0b0.dist-info/METADATA
codelldb-0.1.0b0.dist-info/WHEEL
codelldb-0.1.0b0.dist-info/RECORD
