Metadata-Version: 2.4
Name: codelldb
Version: 0.1.0b0
Summary: Launch CodeLLDB in debugpy to debug rust code.
Project-URL: documentation, https://wsh032.github.io/pytauri/
Project-URL: source, https://github.com/WSH032/pytauri
Author-email: Sean Wang <126865849+WSH032@users.noreply.github.com>
License-Expression: Apache-2.0
Requires-Python: >=3.9
